personio_api_client/__init__.py
personio_api_client/client.py
personio_api_client/exceptions.py
personio_api_client/models.py
personio_api_client-0.1.0.dist-info/METADATA
personio_api_client-0.1.0.dist-info/WHEEL
personio_api_client-0.1.0.dist-info/licenses/LICENSE
personio_api_client-0.1.0.dist-info/RECORD
