Metadata-Version: 2.4
Name: personio-api-client
Version: 0.1.0
Summary: Python client for the Personio REST API
Project-URL: Repository, https://github.com/dkd-dobberkau/personio-api-client
Author: Olivier
License: MIT
License-File: LICENSE
Keywords: api,client,hr,human-resources,personio
Classifier: Development Status :: 4 - Beta
Classifier: Intended Audience :: Developers
Classifier: License :: OSI Approved :: MIT License
Classifier: Programming Language :: Python :: 3
Classifier: Programming Language :: Python :: 3.11
Classifier: Programming Language :: Python :: 3.12
Classifier: Programming Language :: Python :: 3.13
Classifier: Typing :: Typed
Requires-Python: >=3.11
Requires-Dist: httpx>=0.27
Requires-Dist: pydantic>=2.0
Provides-Extra: dev
Requires-Dist: pytest-httpx>=0.30; extra == 'dev'
Requires-Dist: pytest>=8.0; extra == 'dev'
Requires-Dist: ruff>=0.4; extra == 'dev'
